vestacrystparser/__init__.py
vestacrystparser/convert.py
vestacrystparser/export.py
vestacrystparser/parser.py
vestacrystparser/resources/__init__.py
vestacrystparser/resources/default.vesta
vestacrystparser/resources/elements.csv
vestacrystparser/resources/sbond.csv
vestacrystparser-0.2.0.dist-info/licenses/LICENSE
vestacrystparser-0.2.0.dist-info/METADATA
vestacrystparser-0.2.0.dist-info/WHEEL
vestacrystparser-0.2.0.dist-info/top_level.txt
vestacrystparser-0.2.0.dist-info/RECORD
