Metadata-Version: 2.4
Name: vestacrystparser
Version: 0.2.0
Summary: Parser for VESTA crystal structure visualisation files.
Author-email: Bernard Field <bfield@lbl.gov>, Musa Hussein <mhussein@lbl.gov>
Maintainer-email: Bernard Field <bfield@lbl.gov>
License-Expression: MIT
Project-URL: Repository, https://github.com/Griffin-Group/vestacrystparser
Project-URL: Documentation, https://griffin-group.github.io/vestacrystparser/
Classifier: Development Status :: 3 - Alpha
Classifier: Intended Audience :: Science/Research
Classifier: Natural Language :: English
Classifier: Programming Language :: Python
Classifier: Programming Language :: Python :: 3
Classifier: Topic :: File Formats
Classifier: Topic :: Scientific/Engineering :: Chemistry
Classifier: Topic :: Scientific/Engineering :: Physics
Classifier: Topic :: Scientific/Engineering :: Visualization
Requires-Python: >=3.9
License-File: LICENSE
Provides-Extra: pymatgen
Requires-Dist: pymatgen; extra == "pymatgen"
Provides-Extra: dev
Requires-Dist: pytest; extra == "dev"
Requires-Dist: flake8; extra == "dev"
Requires-Dist: autopep8; extra == "dev"
Requires-Dist: pytest-cov; extra == "dev"
Requires-Dist: sphinx; extra == "dev"
Requires-Dist: myst-parser; extra == "dev"
Dynamic: license-file
